spicy_vki/__init__.py
spicy_vki/spicy.py
spicy_vki/utils/_basis_Harmonic.py
spicy_vki/utils/_basis_RBF.py
spicy_vki/utils/_basis_collocation.py
spicy_vki/utils/_extnumpy.py
spicy_vki/utils/_input_checks.py
spicy_vki-1.1.2.dist-info/METADATA
spicy_vki-1.1.2.dist-info/WHEEL
spicy_vki-1.1.2.dist-info/top_level.txt
spicy_vki-1.1.2.dist-info/RECORD
