Metadata-Version: 2.1
Name: spicy-vki
Version: 1.1.2
Summary: SPICY (Super-resolution and Pressure from Image veloCimetrY) is a software developed at the von Karman Institute to perform data assimilation of image velocimetry using constrained Radial Basis Functions (RBF). The framework works for structured data (as produced by cross-correlation-based algorithms in PIV or Optical Flows) and unstructured data (produced by tracking algorithms in PTV).
Home-page: https://github.com/mendezVKI/SPICY_VKI/tree/main/
Author: P. Sperotto, M. Ratz, M. A. Mendez
Author-email: mendez@vki.ac.be
License: BSD (3-clause)
Classifier: Development Status :: 2 - Pre-Alpha
Classifier: Natural Language :: English
Classifier: Programming Language :: Python :: 3
Requires-Python: >=3.8.0
Requires-Dist: numpy>=1.20
Requires-Dist: scikit-learn>=1.0
Requires-Dist: scipy>=1.5
Requires-Dist: shapely>=1.7.0
Requires-Dist: matplotlib>=3.3.0
Requires-Dist: numpydoc>=1.6.0
